nmass/__init__.py
nmass/errors.py
nmass/masscan.py
nmass/nmap.py
nmass/scanner.py
nmass/utils.py
nmass/model/__init__.py
nmass/model/elements.py
nmass/model/enums.py
nmass/model/iflist.py
nmass-0.2.1.dist-info/METADATA
nmass-0.2.1.dist-info/WHEEL
nmass-0.2.1.dist-info/licenses/LICENSE
nmass-0.2.1.dist-info/RECORD
