Metadata-Version: 2.4
Name: nmass
Version: 0.2.1
Summary: A python3 library that makes it easier to use nmap and masscan.
Project-URL: Homepage, https://zrquan.github.io/nmass/
Project-URL: Repository, https://github.com/zrquan/nmass
Project-URL: Documentation, https://zrquan.github.io/nmass/
Author-email: 4shen0ne <4shen.01@gmail.com>
License-File: LICENSE
Keywords: masscan,nmap,python
Classifier: Intended Audience :: Developers
Classifier: Programming Language :: Python
Classifier: Programming Language :: Python :: 3
Classifier: Programming Language :: Python :: 3.10
Classifier: Programming Language :: Python :: 3.11
Classifier: Programming Language :: Python :: 3.12
Classifier: Programming Language :: Python :: 3.13
Classifier: Topic :: Software Development :: Libraries :: Python Modules
Requires-Python: <4.0,>=3.10
Requires-Dist: lxml>=5.3.0
Requires-Dist: pydantic-xml>=2.13.1
Requires-Dist: pydantic>=2.9.2
Requires-Dist: typing-extensions>=4.12.2
